sdwire/__init__.py
sdwire/backend/__init__.py
sdwire/backend/block_device_utils.py
sdwire/backend/detect.py
sdwire/backend/device/sdwire.py
sdwire/backend/device/sdwirec.py
sdwire/backend/device/usb_device.py
sdwire/backend/utils.py
sdwire/constants.py
sdwire/main.py
sdwire-0.3.0.dist-info/LICENSE
sdwire-0.3.0.dist-info/METADATA
sdwire-0.3.0.dist-info/WHEEL
sdwire-0.3.0.dist-info/entry_points.txt
sdwire-0.3.0.dist-info/RECORD
