Metadata-Version: 2.1
Name: sdwire
Version: 0.3.0
Summary: CLI application to interact with Badgerd SDWire devices
License: GPL-3
Author: Talha Can Havadar
Author-email: havadartalha@gmail.com
Requires-Python: >=3.12,<4.0
Classifier: License :: Other/Proprietary License
Classifier: Programming Language :: Python :: 3
Classifier: Programming Language :: Python :: 3.12
Requires-Dist: click (>=8.1.7,<9.0.0)
Requires-Dist: pyftdi (>=0.56.0,<0.57.0)
Requires-Dist: pyusb (>=1.2.1,<2.0.0)
